<annotation>
	<folder />
	<filename>2017_Tesla_Model_X_100D_Front_jpg.rf.ba4f9263acef171a0c6e380ef500acf2.jpg</filename>
	<path>2017_Tesla_Model_X_100D_Front_jpg.rf.ba4f9263acef171a0c6e380ef500acf2.jpg</path>
	<source>
		<database>roboflow.com</database>
	</source>
	<size>
		<width>640</width>
		<height>323</height>
		<depth>3</depth>
	</size>
	<segmented>0</segmented>
	<object>
		<name>car</name>
		<pose>Unspecified</pose>
		<truncated>0</truncated>
		<difficult>0</difficult>
		<occluded>0</occluded>
		<bndbox>
			<xmin>23</xmin>
			<xmax>618</xmax>
			<ymin>35</ymin>
			<ymax>307</ymax>
		</bndbox>
	</object>
</annotation>