<annotation>
	<folder />
	<filename>images5_jpg.rf.19543d58b8d496d81f5f1e90c163d7bc.jpg</filename>
	<path>images5_jpg.rf.19543d58b8d496d81f5f1e90c163d7bc.jpg</path>
	<source>
		<database>roboflow.com</database>
	</source>
	<size>
		<width>640</width>
		<height>415</height>
		<depth>3</depth>
	</size>
	<segmented>0</segmented>
	<object>
		<name>car</name>
		<pose>Unspecified</pose>
		<truncated>0</truncated>
		<difficult>0</difficult>
		<occluded>0</occluded>
		<bndbox>
			<xmin>63</xmin>
			<xmax>588</xmax>
			<ymin>40</ymin>
			<ymax>369</ymax>
		</bndbox>
	</object>
</annotation>